project.v
`timescale 1ns / 1ps

module traffic_light_controller (
    input wire clk,
    input wire reset,
    input wire pedestrian_request,

    // Outputs (Moore machine, so these depend only on state)
    output reg [2:0] ns_light,       // North-South: 3'b100=G, 3'b010=Y, 3'b001=R
    output reg [2:0] ew_light,       // East-West:   3'b100=G, 3'b010=Y, 3'b001=R
    output reg [1:0] ped_light,      // Pedestrian:  2'b10=WALK, 2'b01=DON'T WALK
    output wire [2:0] current_state, // Expose current state for testbench
    output wire ped_request_latched_out, // Debugging
    output wire was_in_ns_phase_out    // Debugging
);

    // --- State Definitions ---
    parameter S_NS_GREEN  = 3'b000;
    parameter S_NS_YELLOW = 3'b001;
    parameter S_EW_GREEN  = 3'b010;
    parameter S_EW_YELLOW = 3'b011;
    parameter S_PED_GREEN = 3'b100;

    // --- State Registers ---
    reg [2:0] state_reg, next_state;

    // --- Timer Logic ---
    parameter GREEN_DURATION  = 10;
    parameter YELLOW_DURATION = 3;
    parameter PED_DURATION    = 5;

    reg [$clog2(GREEN_DURATION > PED_DURATION ? GREEN_DURATION : PED_DURATION) : 0] timer_count;
    wire timer_done;

    // --- Pedestrian Request Latch ---
    reg ped_request_latched;
    
    // --- Phase Memory Register ---
    // This is the new logic to remember which phase to return to.
    reg was_in_ns_phase;

    // --- FSM Sequential Logic (State, Timer, Phase Memory) ---
    always @(posedge clk or posedge reset) begin
        if (reset) begin
            state_reg <= S_NS_GREEN;
            timer_count <= 0;
            was_in_ns_phase <= 1'b0; // Default to EW phase (so it returns to NS)
        end else begin
            // On state change, reset the timer. Otherwise, increment.
            if (next_state != state_reg) begin
                timer_count <= 0;
            end else if (!timer_done) begin
                timer_count <= timer_count + 1;
            end
            
            // Update the state register
            state_reg <= next_state;

            // *** NEW LOGIC for Phase Memory ***
            // Store where we came from *before* we enter PED_GREEN
            // This is evaluated on the same clock as the state change.
            if (next_state == S_PED_GREEN) begin
                if (state_reg == S_NS_YELLOW)
                    was_in_ns_phase <= 1'b1; // We came from NS
                else if (state_reg == S_EW_YELLOW)
                    was_in_ns_phase <= 1'b0; // We came from EW
            end
            // Note: If we stay in PED_GREEN, this reg holds its value.
        end
    end

    // --- Pedestrian Latch Sequential Logic ---
    // This logic is unchanged and correct.
    always @(posedge clk or posedge reset) begin
        if (reset) begin
            ped_request_latched <= 1'b0;
        end 
        // Latch a new request FIRST (highest priority)
        else if (pedestrian_request) begin
            ped_request_latched <= 1'b1;
        end
        // Clear the latch ONLY when we are *about to service it*.
        else if ((state_reg == S_NS_YELLOW && timer_done && ped_request_latched) ||
                 (state_reg == S_EW_YELLOW && timer_done && ped_request_latched)) 
        begin
            ped_request_latched <= 1'b0;
        end
    end

    // --- Timer 'done' Combinational Logic ---
    assign timer_done = 
        (state_reg == S_NS_GREEN  && timer_count == GREEN_DURATION - 1) ||
        (state_reg == S_NS_YELLOW && timer_count == YELLOW_DURATION - 1) ||
        (state_reg == S_EW_GREEN  && timer_count == GREEN_DURATION - 1) ||
        (state_reg == S_EW_YELLOW && timer_count == YELLOW_DURATION - 1) ||
        (state_reg == S_PED_GREEN && timer_count == PED_DURATION - 1);

    // --- FSM Combinational Logic (Next State) ---
    always @(*) begin
        // Default assignment to avoid latches
        next_state = state_reg;

        case (state_reg)
            S_NS_GREEN: begin
                if (timer_done)
                    next_state = S_NS_YELLOW;
            end
            
            S_NS_YELLOW: begin
                if (timer_done) begin
                    if (ped_request_latched)
                        next_state = S_PED_GREEN; // Go to Ped
                    else
                        next_state = S_EW_GREEN;  // Go to EW
                end
            end
            
            S_EW_GREEN: begin
                if (timer_done)
                    next_state = S_EW_YELLOW;
            end
            
            S_EW_YELLOW: begin
                if (timer_done) begin
                    if (ped_request_latched)
                        next_state = S_PED_GREEN; // Go to Ped
                    else
                        next_state = S_NS_GREEN;  // Go to NS
                end
            end
            
            S_PED_GREEN: begin
                if (timer_done) begin
                    // *** THIS IS THE NEW LOGIC ***
                    if (was_in_ns_phase)
                        next_state = S_EW_GREEN; // Resume to EW
                    else
                        next_state = S_NS_GREEN; // Resume to NS
                end
            end

            default: begin
                next_state = S_NS_GREEN; // Safe state
            end
        endcase
    end

    // --- Moore Output Logic (Combinational) ---
    // This logic is unchanged.
    always @(*) begin
        // Default all lights to Red / Don't Walk
        ns_light  = 3'b001; // Red
        ew_light  = 3'b001; // Red
        ped_light = 2'b01;  // Don't Walk

        case (state_reg)
            // *** FIXED: Removed illegal 'break;' statements ***
            S_NS_GREEN:  ns_light = 3'b100;
            S_NS_YELLOW: ns_light = 3'b010;
            S_EW_GREEN:  ew_light = 3'b100;
            S_EW_YELLOW: ew_light = 3'b010;
            S_PED_GREEN: ped_light = 2'b10;
            default: ; // All Red
        endcase
    end
    
    // --- Assign outputs for testbench ---
    assign current_state = state_reg;
    assign ped_request_latched_out = ped_request_latched;
    assign was_in_ns_phase_out = was_in_ns_phase;

endmodule

tb_project.v
// Testbench for traffic_light_controller

`timescale 1ns / 1ps

module tb_traffic_light_controller;

    //----------------------------------------------------------------------
    // 1. Parameters & DUT Instantiation
    //----------------------------------------------------------------------
    localparam CLK_PERIOD = 1000_000_000; // 1 second in ns

    // DUT Inputs
    reg clk;
    reg reset;
    reg pedestrian_request;

    // DUT Outputs
    wire [2:0] ns_light;
    wire [2:0] ew_light;
    wire [1:0] ped_light;
    wire [2:0] current_state;
    wire       ped_latch_status;
    wire       was_in_ns_phase_status; // <-- ADD THIS LINE

    // --- Helper reg for $monitor ---
    reg [63:0] current_state_string; // 64 bits = 8 characters

    // Instantiate the Device Under Test (DUT)
    traffic_light_controller #(
        .GREEN_DURATION(10), // 10 cycles
        .YELLOW_DURATION(3), // 3 cycles
        .PED_DURATION(5)   // 5 cycles
    ) dut (
        .clk(clk),
        .reset(reset),
        .pedestrian_request(pedestrian_request),
        .ns_light(ns_light),
        .ew_light(ew_light),
        .ped_light(ped_light),
        .current_state(current_state),
        .ped_request_latched_out(ped_latch_status),
        .was_in_ns_phase_out(was_in_ns_phase_status) // <-- ADD THIS LINE
    );

    // State definitions for display and checking
    localparam [2:0]
        S_NS_GREEN  = 3'b000,
        S_NS_YELLOW = 3'b001,
        S_EW_GREEN  = 3'b010,
        S_EW_YELLOW = 3'b011,
        S_PED_GREEN = 3'b100;

    //----------------------------------------------------------------------
    // 2. Clock Generator
    //----------------------------------------------------------------------
    initial begin
        clk = 0;
        forever #(CLK_PERIOD / 2) clk = ~clk;
    end

    // Helper logic for $monitor
    always @(current_state) begin
        current_state_string = state_to_string(current_state);
    end

    // Helper task to wait for 'n' clock cycles
    task wait_cycles;
        input integer n;
        begin
            repeat (n) @(posedge clk);
        end
    endtask

    //----------------------------------------------------------------------
    // 3. Test Scenarios
    //----------------------------------------------------------------------
    initial begin
        $dumpfile("simulation_waves.vcd");
        $dumpvars(0, tb_traffic_light_controller);

        $display("-------------------------------------------------");
        $display("Starting Testbench for Traffic Light Controller");
        $display("-------------------------------------------------");
        $monitor("Time: %0t | State: %s | NS: %b | EW: %b | PED: %b | PedReq: %b | LATCH: %b | PHASE: %b",
                 $time, current_state_string, ns_light, ew_light, ped_light, pedestrian_request, ped_latch_status, was_in_ns_phase_status); // <-- EDIT THIS LINE

        // --- Scenario 1: Reset and Normal Operation ---
        $display("\n[Scenario 1] Reset and Normal Cycle (No Ped Request)");
        reset = 1;
        pedestrian_request = 0;
        wait_cycles(2);

        reset = 0;
        $display("Reset released. Running for 2 full cycles...");
        wait_cycles(26 * 2);

        // --- Scenario 2: Pedestrian Request during NS_GREEN ---
        $display("\n[Scenario 2] Ped Request during NS_GREEN (Tests starvation fix)");
        @(posedge clk); 
        while (current_state != S_NS_GREEN) @(posedge clk);
        
        wait_cycles(2); // Wait 2 cycles into the green
        $display("--> Issuing pedestrian request at time %0t", $time);
        pedestrian_request = 1;
        @(posedge clk);
        pedestrian_request = 0;

        // FSM should cycle: NS_G (8) -> NS_Y (3) -> PED_G (5) -> EW_G (10)
        // We wait to see it enter the *next* state (EW_Y)
        $display("...Verifying FSM goes to EW_GREEN after PED_GREEN...");
        wait_cycles(8 + 3 + 5 + 10 + 2);

        // --- Scenario 3: Back-to-Back Request (during PED_GREEN) ---
        $display("\n[Scenario 3] Back-to-Back Ped Request (during PED_GREEN)");
        @(posedge clk);
        while (current_state != S_NS_GREEN) @(posedge clk);
        
        wait_cycles(2);
        $display("--> Issuing 1st request at time %0t", $time);
        pedestrian_request = 1;
        @(posedge clk);
        pedestrian_request = 0;

        // Wait until we are in the PED_GREEN state
        @(posedge clk); 
        while (current_state != S_PED_GREEN) @(posedge clk);
        
        wait_cycles(1);
        $display("--> FSM is in PED_GREEN. Issuing 2nd request at time %0t", $time);
        pedestrian_request = 1;
        @(posedge clk);
        pedestrian_request = 0;

        // FSM should:
        // 1. Finish PED_GREEN (4 cycles left), resume to EW_GREEN
        // 2. Run EW_GREEN (10)
        // 3. Run EW_YELLOW (3)
        // 4. Service 2nd request -> PED_GREEN (5)
        // 5. Resume to NS_GREEN
        $display("...Verifying FSM completes full cycle before servicing 2nd request...");
        wait_cycles(4 + 10 + 3 + 5 + 5); 

        $display("\n[Testbench] All scenarios complete.");
        $finish;
    end

    // Helper function for nice $monitor output
    function [63:0] state_to_string; // 64 bits = 8 characters
        input [2:0] state;
        case (state)
            S_NS_GREEN:  state_to_string = "NS_GRN";
            S_NS_YELLOW: state_to_string = "NS_YEL";
            S_EW_GREEN:  state_to_string = "EW_GRN";
            S_EW_YELLOW: state_to_string = "EW_YEL";
            S_PED_GREEN: state_to_string = "PED_GRN";
            default:     state_to_string = "XXXXXX";
        endcase
    endfunction

endmodule

simulation_waves.vcd
$date
	Sun Nov 09 01:38:27 2025
$end
$version
	Icarus Verilog
$end
$timescale
	1ps
$end
$scope module tb_traffic_light_controller $end
$var wire 1 ! was_in_ns_phase_status $end
$var wire 2 " ped_light [1:0] $end
$var wire 1 # ped_latch_status $end
$var wire 3 $ ns_light [2:0] $end
$var wire 3 % ew_light [2:0] $end
$var wire 3 & current_state [2:0] $end
$var parameter 32 ' CLK_PERIOD $end
$var parameter 3 ( S_EW_GREEN $end
$var parameter 3 ) S_EW_YELLOW $end
$var parameter 3 * S_NS_GREEN $end
$var parameter 3 + S_NS_YELLOW $end
$var parameter 3 , S_PED_GREEN $end
$var reg 1 - clk $end
$var reg 64 . current_state_string [63:0] $end
$var reg 1 / pedestrian_request $end
$var reg 1 0 reset $end
$scope function state_to_string $end
$var reg 3 1 state [2:0] $end
$upscope $end
$scope module dut $end
$var wire 1 - clk $end
$var wire 3 2 current_state [2:0] $end
$var wire 1 # ped_request_latched_out $end
$var wire 1 / pedestrian_request $end
$var wire 1 0 reset $end
$var wire 1 3 timer_done $end
$var wire 1 ! was_in_ns_phase_out $end
$var parameter 32 4 GREEN_DURATION $end
$var parameter 32 5 PED_DURATION $end
$var parameter 3 6 S_EW_GREEN $end
$var parameter 3 7 S_EW_YELLOW $end
$var parameter 3 8 S_NS_GREEN $end
$var parameter 3 9 S_NS_YELLOW $end
$var parameter 3 : S_PED_GREEN $end
$var parameter 32 ; YELLOW_DURATION $end
$var reg 3 < ew_light [2:0] $end
$var reg 3 = next_state [2:0] $end
$var reg 3 > ns_light [2:0] $end
$var reg 2 ? ped_light [1:0] $end
$var reg 1 @ ped_request_latched $end
$var reg 3 A state_reg [2:0] $end
$var reg 5 B timer_count [4:0] $end
$var reg 1 C was_in_ns_phase $end
$upscope $end
$scope task wait_cycles $end
$var integer 32 D n [31:0] $end
$upscope $end
$upscope $end
$enddefinitions $end
$comment Show the parameter values. $end
$dumpall
b11 ;
b100 :
b1 9
b0 8
b11 7
b10 6
b101 5
b1010 4
b100 ,
b1 +
b0 *
b11 )
b10 (
b111011100110101100101000000000 '
$end
#0
$dumpvars
b10 D
0C
b0 B
b0 A
0@
b1 ?
b100 >
b0 =
b1 <
03
b0 2
b0 1
10
0/
b10011100101001101011111010001110101001001001110 .
0-
b0 &
b1 %
b100 $
0#
b1 "
0!
$end
#500000000000
1-
#1000000000000
0-
#1500000000000
b1 B
b110100 D
00
1-
#2000000000000
0-
#2500000000000
b10 B
1-
#3000000000000
0-
#3500000000000
b11 B
1-
#4000000000000
0-
#4500000000000
b100 B
1-
#5000000000000
0-
#5500000000000
b101 B
1-
#6000000000000
0-
#6500000000000
b110 B
1-
#7000000000000
0-
#7500000000000
b111 B
1-
#8000000000000
0-
#8500000000000
b1000 B
1-
#9000000000000
0-
#9500000000000
b1 =
13
b1001 B
1-
#10000000000000
0-
#10500000000000
03
b10 $
b10 >
b1 =
b10011100101001101011111010110010100010101001100 .
b1 1
b1 &
b1 2
b1 A
b0 B
1-
#11000000000000
0-
#11500000000000
b1 B
1-
#12000000000000
0-
#12500000000000
b10 =
13
b10 B
1-
#13000000000000
0-
#13500000000000
03
b100 %
b100 <
b1 $
b1 >
b10 =
b10001010101011101011111010001110101001001001110 .
b10 1
b10 &
b10 2
b10 A
b0 B
1-
#14000000000000
0-
#14500000000000
b1 B
1-
#15000000000000
0-
#15500000000000
b10 B
1-
#16000000000000
0-
#16500000000000
b11 B
1-
#17000000000000
0-
#17500000000000
b100 B
1-
#18000000000000
0-
#18500000000000
b101 B
1-
#19000000000000
0-
#19500000000000
b110 B
1-
#20000000000000
0-
#20500000000000
b111 B
1-
#21000000000000
0-
#21500000000000
b1000 B
1-
#22000000000000
0-
#22500000000000
b11 =
13
b1001 B
1-
#23000000000000
0-
#23500000000000
03
b10 %
b10 <
b11 =
b10001010101011101011111010110010100010101001100 .
b11 1
b11 &
b11 2
b11 A
b0 B
1-
#24000000000000
0-
#24500000000000
b1 B
1-
#25000000000000
0-
#25500000000000
b0 =
13
b10 B
1-
#26000000000000
0-
#26500000000000
03
b100 $
b100 >
b1 %
b1 <
b0 =
b10011100101001101011111010001110101001001001110 .
b0 1
b0 &
b0 2
b0 A
b0 B
1-
#27000000000000
0-
#27500000000000
b1 B
1-
#28000000000000
0-
#28500000000000
b10 B
1-
#29000000000000
0-
#29500000000000
b11 B
1-
#30000000000000
0-
#30500000000000
b100 B
1-
#31000000000000
0-
#31500000000000
b101 B
1-
#32000000000000
0-
#32500000000000
b110 B
1-
#33000000000000
0-
#33500000000000
b111 B
1-
#34000000000000
0-
#34500000000000
b1000 B
1-
#35000000000000
0-
#35500000000000
b1 =
13
b1001 B
1-
#36000000000000
0-
#36500000000000
03
b10 $
b10 >
b1 =
b10011100101001101011111010110010100010101001100 .
b1 1
b1 &
b1 2
b1 A
b0 B
1-
#37000000000000
0-
#37500000000000
b1 B
1-
#38000000000000
0-
#38500000000000
b10 =
13
b10 B
1-
#39000000000000
0-
#39500000000000
03
b100 %
b100 <
b1 $
b1 >
b10 =
b10001010101011101011111010001110101001001001110 .
b10 1
b10 &
b10 2
b10 A
b0 B
1-
#40000000000000
0-
#40500000000000
b1 B
1-
#41000000000000
0-
#41500000000000
b10 B
1-
#42000000000000
0-
#42500000000000
b11 B
1-
#43000000000000
0-
#43500000000000
b100 B
1-
#44000000000000
0-
#44500000000000
b101 B
1-
#45000000000000
0-
#45500000000000
b110 B
1-
#46000000000000
0-
#46500000000000
b111 B
1-
#47000000000000
0-
#47500000000000
b1000 B
1-
#48000000000000
0-
#48500000000000
b11 =
13
b1001 B
1-
#49000000000000
0-
#49500000000000
03
b10 %
b10 <
b11 =
b10001010101011101011111010110010100010101001100 .
b11 1
b11 &
b11 2
b11 A
b0 B
1-
#50000000000000
0-
#50500000000000
b1 B
1-
#51000000000000
0-
#51500000000000
b0 =
13
b10 B
1-
#52000000000000
0-
#52500000000000
03
b100 $
b100 >
b1 %
b1 <
b0 =
b10011100101001101011111010001110101001001001110 .
b0 1
b0 &
b0 2
b0 A
b0 B
1-
#53000000000000
0-
#53500000000000
b1 B
1-
#54000000000000
0-
#54500000000000
b10 B
b10 D
1-
#55000000000000
0-
#55500000000000
b11 B
1-
#56000000000000
0-
#56500000000000
1#
1@
b100 B
1/
1-
#57000000000000
0-
#57500000000000
b101 B
b11100 D
0/
1-
#58000000000000
0-
#58500000000000
b110 B
1-
#59000000000000
0-
#59500000000000
b111 B
1-
#60000000000000
0-
#60500000000000
b1000 B
1-
#61000000000000
0-
#61500000000000
b1 =
13
b1001 B
1-
#62000000000000
0-
#62500000000000
03
b10 $
b10 >
b1 =
b10011100101001101011111010110010100010101001100 .
b1 1
b1 &
b1 2
b1 A
b0 B
1-
#63000000000000
0-
#63500000000000
b1 B
1-
#64000000000000
0-
#64500000000000
b100 =
13
b10 B
1-
#65000000000000
0-
#65500000000000
03
b10 "
b10 ?
b1 $
b1 >
b1010000010001010100010001011111010001110101001001001110 .
b100 1
b100 =
1!
1C
b100 &
b100 2
b100 A
b0 B
0#
0@
1-
#66000000000000
0-
#66500000000000
b1 B
1-
#67000000000000
0-
#67500000000000
b10 B
1-
#68000000000000
0-
#68500000000000
b11 B
1-
#69000000000000
0-
#69500000000000
b10 =
13
b100 B
1-
#70000000000000
0-
#70500000000000
03
b100 %
b100 <
b1 "
b1 ?
b10 =
b10001010101011101011111010001110101001001001110 .
b10 1
b10 &
b10 2
b10 A
b0 B
1-
#71000000000000
0-
#71500000000000
b1 B
1-
#72000000000000
0-
#72500000000000
b10 B
1-
#73000000000000
0-
#73500000000000
b11 B
1-
#74000000000000
0-
#74500000000000
b100 B
1-
#75000000000000
0-
#75500000000000
b101 B
1-
#76000000000000
0-
#76500000000000
b110 B
1-
#77000000000000
0-
#77500000000000
b111 B
1-
#78000000000000
0-
#78500000000000
b1000 B
1-
#79000000000000
0-
#79500000000000
b11 =
13
b1001 B
1-
#80000000000000
0-
#80500000000000
03
b10 %
b10 <
b11 =
b10001010101011101011111010110010100010101001100 .
b11 1
b11 &
b11 2
b11 A
b0 B
1-
#81000000000000
0-
#81500000000000
b1 B
1-
#82000000000000
0-
#82500000000000
b0 =
13
b10 B
1-
#83000000000000
0-
#83500000000000
03
b100 $
b100 >
b1 %
b1 <
b0 =
b10011100101001101011111010001110101001001001110 .
b0 1
b0 &
b0 2
b0 A
b0 B
1-
#84000000000000
0-
#84500000000000
b1 B
1-
#85000000000000
0-
#85500000000000
b10 B
1-
#86000000000000
0-
#86500000000000
b11 B
b10 D
1-
#87000000000000
0-
#87500000000000
b100 B
1-
#88000000000000
0-
#88500000000000
1#
1@
b101 B
1/
1-
#89000000000000
0-
#89500000000000
b110 B
0/
1-
#90000000000000
0-
#90500000000000
b111 B
1-
#91000000000000
0-
#91500000000000
b1000 B
1-
#92000000000000
0-
#92500000000000
b1 =
13
b1001 B
1-
#93000000000000
0-
#93500000000000
03
b10 $
b10 >
b1 =
b10011100101001101011111010110010100010101001100 .
b1 1
b1 &
b1 2
b1 A
b0 B
1-
#94000000000000
0-
#94500000000000
b1 B
1-
#95000000000000
0-
#95500000000000
b100 =
13
b10 B
1-
#96000000000000
0-
#96500000000000
03
b10 "
b10 ?
b1 $
b1 >
b100 =
b1010000010001010100010001011111010001110101001001001110 .
b100 1
0#
0@
b100 &
b100 2
b100 A
b0 B
1-
#97000000000000
0-
#97500000000000
b1 B
b1 D
1-
#98000000000000
0-
#98500000000000
1#
1@
b10 B
1/
1-
#99000000000000
0-
#99500000000000
b11 B
b11011 D
0/
1-
#100000000000000
0-
#100500000000000
b10 =
13
b100 B
1-
#101000000000000
0-
#101500000000000
03
b100 %
b100 <
b1 "
b1 ?
b10 =
b10001010101011101011111010001110101001001001110 .
b10 1
b10 &
b10 2
b10 A
b0 B
1-
#102000000000000
0-
#102500000000000
b1 B
1-
#103000000000000
0-
#103500000000000
b10 B
1-
#104000000000000
0-
#104500000000000
b11 B
1-
#105000000000000
0-
#105500000000000
b100 B
1-
#106000000000000
0-
#106500000000000
b101 B
1-
#107000000000000
0-
#107500000000000
b110 B
1-
#108000000000000
0-
#108500000000000
b111 B
1-
#109000000000000
0-
#109500000000000
b1000 B
1-
#110000000000000
0-
#110500000000000
b11 =
13
b1001 B
1-
#111000000000000
0-
#111500000000000
03
b10 %
b10 <
b11 =
b10001010101011101011111010110010100010101001100 .
b11 1
b11 &
b11 2
b11 A
b0 B
1-
#112000000000000
0-
#112500000000000
b1 B
1-
#113000000000000
0-
#113500000000000
b100 =
13
b10 B
1-
#114000000000000
0-
#114500000000000
03
b10 "
b10 ?
b1 %
b1 <
b100 =
b1010000010001010100010001011111010001110101001001001110 .
b100 1
0#
0@
0!
0C
b100 &
b100 2
b100 A
b0 B
1-
#115000000000000
0-
#115500000000000
b1 B
1-
#116000000000000
0-
#116500000000000
b10 B
1-
#117000000000000
0-
#117500000000000
b11 B
1-
#118000000000000
0-
#118500000000000
b0 =
13
b100 B
1-
#119000000000000
0-
#119500000000000
03
b100 $
b100 >
b1 "
b1 ?
b0 =
b10011100101001101011111010001110101001001001110 .
b0 1
b0 &
b0 2
b0 A
b0 B
1-
#120000000000000
0-
#120500000000000
b1 B
1-
#121000000000000
0-
#121500000000000
b10 B
1-
#122000000000000
0-
#122500000000000
b11 B
1-
#123000000000000
0-
#123500000000000
b100 B
1-
#124000000000000
0-
#124500000000000
b101 B
1-
#125000000000000
0-
#125500000000000
b110 B
1-
#126000000000000
0-
#126500000000000
b111 B
1-
